{ "compressionlevel":-1,
 "height":40,
 "infinite":false,
 "layers":[
        {
         "compression":"zlib",
         "data":"eJzt1UsOgjAURuGqQ3Fu3IRO3f\/GhNn1htY+Iv0L50saJ00RTriEAAAAAAAAerv1\/gP4Qg8t9Cgz\/fl8emihhxZ6aKGHFnpoGaHHaV7nzHVpPMfLuear5eZmT3PWCD2uBXtT97OcM\/1YW1tavM31j9ZDgX0fbAt6bM+\/D37dQ\/5sXpuv3tqMjs302Dz3+0frkXp+qRYlK5jf0hkd2x+b537\/aD1a1HRJoUeb2nclhh5t9tYj9T18FJzTS00P5e\/H6OihhR5a6KGFHgAAAABwTB9hoRDh",
         "encoding":"base64",
         "height":40,
         "id":1,
         "name":"Tile Layer 1",
         "opacity":1,
         "type":"tilelayer",
         "visible":true,
         "width":100,
         "x":0,
         "y":0
        }],
 "nextlayerid":2,
 "nextobjectid":1,
 "orientation":"orthogonal",
 "renderorder":"right-down",
 "tiledversion":"1.10.2",
 "tileheight":32,
 "tilesets":[
        {
         "columns":10,
         "firstgid":1,
         "image":"..\/Level Tiles\/1 Tiles\/Tileset.png",
         "imageheight":192,
         "imagewidth":320,
         "margin":0,
         "name":"ForestTiles",
         "spacing":0,
         "tilecount":60,
         "tileheight":32,
         "tiles":[
                {
                 "id":0,
                 "type":"Ground"
                }, 
                {
                 "id":1,
                 "type":"Ground"
                }, 
                {
                 "id":2,
                 "type":"Ground"
                }, 
                {
                 "id":10,
                 "type":"Wall"
                }, 
                {
                 "id":11,
                 "type":"Wall"
                }, 
                {
                 "id":12,
                 "type":"Wall"
                }, 
                {
                 "id":20,
                 "type":"Wall"
                }, 
                {
                 "id":22,
                 "type":"Wall"
                }],
         "tilewidth":32
        }],
 "tilewidth":32,
 "type":"map",
 "version":"1.10",
 "width":100
}